forgepb/__init__.py
forgepb/__main__.py
forgepb/builder.py
forgepb/command_line.py
forgepb/config_handler.py
forgepb/forge.py
forgepb/global_.py
forgepb/utils.py
forgepb/cmd/__init__.py
forgepb/cmd/config.py
forgepb/cmd/node.py
forgepb/cmd/provenance.py
forge.pb-1.0.5.dist-info/LICENSE
forge.pb-1.0.5.dist-info/METADATA
forge.pb-1.0.5.dist-info/WHEEL
forge.pb-1.0.5.dist-info/entry_points.txt
forge.pb-1.0.5.dist-info/top_level.txt
forge.pb-1.0.5.dist-info/RECORD
