Metadata-Version: 2.1
Name: forge.pb
Version: 1.0.5
Summary: Node manager for the Provenance Blockchain
Home-page: https://github.com/provenance-io/forge.pb
Author: Wyatt Baker
Author-email: wbaker@figure.com
Requires-Python: >=3.7
License-File: LICENSE
Requires-Dist: arrow ==1.2.3
Requires-Dist: certifi ==2023.7.22
Requires-Dist: charset-normalizer ==3.2.0
Requires-Dist: click ==8.1.7
Requires-Dist: decorator ==4.4.2
Requires-Dist: futures ==2.2.0
Requires-Dist: gitdb ==4.0.10
Requires-Dist: GitPython ==3.1.32
Requires-Dist: idna ==3.3
Requires-Dist: importlib-metadata ==4.13.0
Requires-Dist: networkx ==2.8.8
Requires-Dist: psutil ==5.9.5
Requires-Dist: python-dateutil ==2.8.2
Requires-Dist: requests ==2.31.0
Requires-Dist: six ==1.16.0
Requires-Dist: smmap ==5.0.0
Requires-Dist: tornado ==6.3.3
Requires-Dist: typing-extensions ==4.7.1
Requires-Dist: urllib3 ==1.26.16
Requires-Dist: zipp ==3.16.2
